MANIFEST.in
README.rst
setup.py
AlgoTrading/__init__.py
AlgoTrading.egg-info/PKG-INFO
AlgoTrading.egg-info/SOURCES.txt
AlgoTrading.egg-info/dependency_links.txt
AlgoTrading.egg-info/requires.txt
AlgoTrading.egg-info/top_level.txt
AlgoTrading/Assets/Futures.py
AlgoTrading/Assets/Indexes.py
AlgoTrading/Assets/MutualFunds.py
AlgoTrading/Assets/Stocks.py
AlgoTrading/Assets/__init__.py
AlgoTrading/Assets/base.py
AlgoTrading/Backtest/Backtest.py
AlgoTrading/Backtest/SignalRunner.py
AlgoTrading/Backtest/StrategyRunner.py
AlgoTrading/Backtest/__init__.py
AlgoTrading/Data/Data.py
AlgoTrading/Data/__init__.py
AlgoTrading/Data/DataProviders/CSVFiles.py
AlgoTrading/Data/DataProviders/DataYes.py
AlgoTrading/Data/DataProviders/DongXingDataCenter.py
AlgoTrading/Data/DataProviders/YaHoo.py
AlgoTrading/Data/DataProviders/__init__.py
AlgoTrading/Enums/__init__.py
AlgoTrading/Env/Settings.py
AlgoTrading/Env/__init__.py
AlgoTrading/Events/Event.py
AlgoTrading/Events/FillEvent.py
AlgoTrading/Events/MarketEvent.py
AlgoTrading/Events/OrderEvent.py
AlgoTrading/Events/ScheduleEvent.py
AlgoTrading/Events/SignalEvent.py
AlgoTrading/Events/__init__.py
AlgoTrading/Execution/Execution.py
AlgoTrading/Execution/FilledBook.py
AlgoTrading/Execution/OrderBook.py
AlgoTrading/Execution/__init__.py
AlgoTrading/Finance/Commission.py
AlgoTrading/Finance/__init__.py
AlgoTrading/Portfolio/Portfolio.py
AlgoTrading/Portfolio/PositionsBook.py
AlgoTrading/Portfolio/__init__.py
AlgoTrading/Strategy/InfoKeeper.py
AlgoTrading/Strategy/Signal.py
AlgoTrading/Strategy/Strategy.py
AlgoTrading/Strategy/__init__.py
AlgoTrading/Utilities/Logger.py
AlgoTrading/Utilities/Parsers.py
AlgoTrading/Utilities/__init__.py
AlgoTrading/Utilities/functions.py
AlgoTrading/api/__init__.py
AlgoTrading/examples/BondFuturesStrategy.py
AlgoTrading/examples/CatchMomentumStrategy.py
AlgoTrading/examples/DataYesBasedStrategy.py
AlgoTrading/examples/DongXingSample.py
AlgoTrading/examples/DongXingSampleWithContinuingContract.py
AlgoTrading/examples/FilteredFactorsStrategy.py
AlgoTrading/examples/FuturesExample.py
AlgoTrading/examples/IndexMomentumStrategy.py
AlgoTrading/examples/IndexMonitoring.py
