Metadata-Version: 1.0
Name: AlgoTrading
Version: 0.2.1
Summary: algorithmic trading framework for multiple assets
Home-page: https://github.com/ChinaQuants/AlgoTrading
Author: cheng li
Author-email: wegamekinglc@hotmail.com
License: UNKNOWN
Platform: UNKNOWN
